odoo/addons/stock_inventory_valuation_show_remaining/README.rst
odoo/addons/stock_inventory_valuation_show_remaining/__init__.py
odoo/addons/stock_inventory_valuation_show_remaining/__manifest__.py
odoo/addons/stock_inventory_valuation_show_remaining/i18n/stock_inventory_valuation_show_remaining.pot
odoo/addons/stock_inventory_valuation_show_remaining/readme/CONTRIBUTORS.rst
odoo/addons/stock_inventory_valuation_show_remaining/readme/DESCRIPTION.rst
odoo/addons/stock_inventory_valuation_show_remaining/static/description/icon.png
odoo/addons/stock_inventory_valuation_show_remaining/static/description/index.html
odoo/addons/stock_inventory_valuation_show_remaining/views/stock_valuation_layer_views.xml
odoo13_addon_stock_inventory_valuation_show_remaining-13.0.1.0.1.dev3.dist-info/METADATA
odoo13_addon_stock_inventory_valuation_show_remaining-13.0.1.0.1.dev3.dist-info/WHEEL
odoo13_addon_stock_inventory_valuation_show_remaining-13.0.1.0.1.dev3.dist-info/top_level.txt
odoo13_addon_stock_inventory_valuation_show_remaining-13.0.1.0.1.dev3.dist-info/RECORD
